README.md
setup.py
pulumiverse_clickhouse/__init__.py
pulumiverse_clickhouse/_inputs.py
pulumiverse_clickhouse/_utilities.py
pulumiverse_clickhouse/outputs.py
pulumiverse_clickhouse/provider.py
pulumiverse_clickhouse/pulumi-plugin.json
pulumiverse_clickhouse/py.typed
pulumiverse_clickhouse/service.py
pulumiverse_clickhouse.egg-info/PKG-INFO
pulumiverse_clickhouse.egg-info/SOURCES.txt
pulumiverse_clickhouse.egg-info/dependency_links.txt
pulumiverse_clickhouse.egg-info/not-zip-safe
pulumiverse_clickhouse.egg-info/requires.txt
pulumiverse_clickhouse.egg-info/top_level.txt
pulumiverse_clickhouse/config/__init__.py
pulumiverse_clickhouse/config/vars.py
pulumiverse_clickhouse/privateendpoint/__init__.py
pulumiverse_clickhouse/privateendpoint/get_config.py
pulumiverse_clickhouse/privateendpoint/registration.py
pulumiverse_clickhouse/serviceprivateendpoints/__init__.py
pulumiverse_clickhouse/serviceprivateendpoints/attachment.py