Metadata-Version: 2.1
Name: pulumiverse-clickhouse
Version: 1.0.1
Summary: A Pulumi package for creating and managing Clickhouse Cloud resources
Home-page: https://github.com/pulumiverse/pulumi-clickhouse
License: Apache-2.0
Project-URL: Repository, https://github.com/pulumiverse/pulumi-clickhouse
Keywords: pulumi clickhouse category/cloud
Platform: UNKNOWN
Requires-Python: >=3.8
